MANIFEST.in
README.rst
setup.py
django_tcms.egg-info/PKG-INFO
django_tcms.egg-info/SOURCES.txt
django_tcms.egg-info/dependency_links.txt
django_tcms.egg-info/requires.txt
django_tcms.egg-info/top_level.txt
tcms/__init__.py
tcms/admin.py
tcms/context_processors.py
tcms/data_types.py
tcms/exceptions.py
tcms/fields.py
tcms/forms.py
tcms/models.py
tcms/sitemap.py
tcms/tpl.py
tcms/utils.py
tcms/views.py
tcms/static/css/cms.css
tcms/static/css/fancybox.css
tcms/static/img/copy.png
tcms/static/img/delete.png
tcms/static/img/delete_disabled.png
tcms/static/img/edit.png
tcms/static/img/loading.gif
tcms/static/img/log.png
tcms/static/img/nav-bg.gif
tcms/static/img/package.png
tcms/static/img/preview.png
tcms/static/img/publish.png
tcms/static/img/refresh.png
tcms/static/img/refresh_disabled.png
tcms/static/img/unpublish.png
tcms/static/img/fancybox/blank.gif
tcms/static/img/fancybox/fancy_close.png
tcms/static/img/fancybox/fancy_loading.png
tcms/static/img/fancybox/fancy_nav_left.png
tcms/static/img/fancybox/fancy_nav_right.png
tcms/static/img/fancybox/fancy_shadow_e.png
tcms/static/img/fancybox/fancy_shadow_n.png
tcms/static/img/fancybox/fancy_shadow_ne.png
tcms/static/img/fancybox/fancy_shadow_nw.png
tcms/static/img/fancybox/fancy_shadow_s.png
tcms/static/img/fancybox/fancy_shadow_se.png
tcms/static/img/fancybox/fancy_shadow_sw.png
tcms/static/img/fancybox/fancy_shadow_w.png
tcms/static/img/fancybox/fancy_title_left.png
tcms/static/img/fancybox/fancy_title_main.png
tcms/static/img/fancybox/fancy_title_over.png
tcms/static/img/fancybox/fancy_title_right.png
tcms/static/img/fancybox/fancybox-x.png
tcms/static/img/fancybox/fancybox-y.png
tcms/static/img/fancybox/fancybox.png
tcms/static/js/ckeditor_config.js
tcms/static/js/cms.js
tcms/static/js/jquery.fancybox.js
tcms/static/js/jquery.form.js
tcms/static/js/jquery.mousewheel.js
tcms/templates/cms/cms_base.html
tcms/templates/cms/copy.html
tcms/templates/cms/edit.html
tcms/templates/cms/edit_section.html
tcms/templates/cms/form_fields.html
tcms/templates/cms/import.html
tcms/templates/cms/page_change_list.html
tcms/templates/cms/page_history.html
tcms/templates/cms/rawid.html
