Metadata-Version: 1.0
Name: django-tcms
Version: 0.1.8
Summary: Django tCMS.
Home-page: https://github.com/omab/django-tcms
Author: Matías Aguirre
Author-email: matiasaguirre@gmail.com
License: BSD
Keywords: django,cms,django-admin
Platform: UNKNOWN
Classifier: Framework :: Django
Classifier: Development Status :: 4 - Beta
Classifier: Topic :: Internet
Classifier: License :: OSI Approved :: BSD License
Classifier: Intended Audience :: Developers
Classifier: Environment :: Web Environment
Classifier: Programming Language :: Python :: 2.5
Classifier: Programming Language :: Python :: 2.6
Classifier: Programming Language :: Python :: 2.7
